Metadata-Version: 1.0
Name: jzrki-linear-system
Version: 0.1.1
Summary: Solve a System of N-dimensional Linear Equations
Home-page: UNKNOWN
Author: James L Zhang
Author-email: jzr.kingsta@outlook.com
License: UNKNOWN
Platform: UNKNOWN
